swiftnbd-0.9.7.dist-info/DESCRIPTION.rst
swiftnbd-0.9.7.dist-info/pydist.json
swiftnbd-0.9.7.dist-info/top_level.txt
swiftnbd-0.9.7.dist-info/WHEEL
swiftnbd-0.9.7.dist-info/METADATA
swiftnbd-0.9.7.dist-info/RECORD
swiftnbd-0.9.7.data/scripts/swiftnbd-server
swiftnbd-0.9.7.data/scripts/swiftnbd-ctl
swiftnbd/const.py
swiftnbd/swift.py
swiftnbd/common.py
swiftnbd/main.py
swiftnbd/control.py
swiftnbd/server.py
swiftnbd/cache.py
swiftnbd/__init__.py
