Metadata-Version: 2.0
Name: swiftnbd
Version: 0.9.7
Summary: This is a NBD server for OpenStack Object Storage (Swift).
Home-page: https://github.com/reidrac/swift-nbd-server
Author: Juan J. Martinez
Author-email: jjm@usebox.net
License: MIT
Keywords: openstack object storage swift nbd
Platform: UNKNOWN
Classifier: Development Status :: 4 - Beta
Classifier: Environment :: Console
Classifier: Programming Language :: Python
Classifier: Operating System :: OS Independent
Classifier: Environment :: No Input/Output (Daemon)
Classifier: License :: OSI Approved :: MIT License
Requires-Dist: python-swiftclient (>=1.2.0)
Requires-Dist: gevent (>=0.13.8)
